[
    {
        "link": "https://www.bbc.com/sport/football/articles/clyrp14yx75o",
        "Topics": [
            "Premier League",
            "Manchester City",
            "Football"
        ]
    },
    {
        "link": "https://www.bbc.com/sport/tennis/articles/c0k82g8lzn0o",
        "Topics": [
            "Tennis"
        ]
    },
    {
        "link": "https://www.bbc.com/sport/football/articles/cde7p7yy6nno",
        "Topics": [
            "Premier League",
            "Tottenham Hotspur",
            "Football"
        ]
    },
    {
        "link": "https://www.bbc.com/sport/football/articles/cdxyk2777keo",
        "Topics": [
            "Premier League",
            "Football"
        ]
    },
    {
        "link": "https://www.bbc.com/sport/football/articles/cwy5k0gq2vgo",
        "Topics": [
            "FIFA Women's World Cup",
            "Football",
            "Women's Football"
        ]
    }
]